agentstate/__init__.py
agentstate/client.py
agentstate-1.0.2.dist-info/METADATA
agentstate-1.0.2.dist-info/WHEEL
agentstate-1.0.2.dist-info/top_level.txt
agentstate-1.0.2.dist-info/RECORD
