Metadata-Version: 2.4
Name: agentstate
Version: 1.0.2
Summary: Firebase for AI Agents - Persistent state management for AI applications
Home-page: https://github.com/ayushmi/agentstate
Author: Ayush Mittal
Author-email: ayushsmittal@gmail.com
Project-URL: Bug Tracker, https://github.com/ayushmi/agentstate/issues
Project-URL: Documentation, https://github.com/ayushmi/agentstate#readme
Project-URL: Source Code, https://github.com/ayushmi/agentstate
Keywords: ai agents state management firebase persistent storage real-time
Classifier: Development Status :: 5 - Production/Stable
Classifier: Intended Audience :: Developers
Classifier: License :: OSI Approved :: MIT License
Classifier: Operating System :: OS Independent
Classifier: Programming Language :: Python :: 3
Classifier: Programming Language :: Python :: 3.9
Classifier: Programming Language :: Python :: 3.10
Classifier: Programming Language :: Python :: 3.11
Classifier: Programming Language :: Python :: 3.12
Classifier: Topic :: Software Development :: Libraries :: Python Modules
Classifier: Topic :: Internet :: WWW/HTTP :: HTTP Servers
Classifier: Topic :: Scientific/Engineering :: Artificial Intelligence
Requires-Python: >=3.9
Requires-Dist: requests>=2.25.0
Provides-Extra: dev
Requires-Dist: pytest>=7.0.0; extra == "dev"
Requires-Dist: black>=22.0.0; extra == "dev"
Requires-Dist: isort>=5.10.0; extra == "dev"
Requires-Dist: mypy>=1.0.0; extra == "dev"
Provides-Extra: grpc
Requires-Dist: grpcio>=1.50.0; extra == "grpc"
Requires-Dist: protobuf>=4.0.0; extra == "grpc"
Dynamic: author
Dynamic: author-email
Dynamic: classifier
Dynamic: description
Dynamic: description-content-type
Dynamic: home-page
Dynamic: keywords
Dynamic: project-url
Dynamic: provides-extra
Dynamic: requires-dist
Dynamic: requires-python
Dynamic: summary
